setup.py
django_auth_kerberos/__init__.py
django_auth_kerberos/backends.py
django_auth_kerberos/tests.py
django_auth_kerberos/views.py
django_auth_kerberos.egg-info/PKG-INFO
django_auth_kerberos.egg-info/SOURCES.txt
django_auth_kerberos.egg-info/dependency_links.txt
django_auth_kerberos.egg-info/requires.txt
django_auth_kerberos.egg-info/top_level.txt