Metadata-Version: 1.1
Name: django-auth-kerberos
Version: 1.2.3
Summary: Kerberos authentication backend for Django
Home-page: https://github.com/02strich/django-auth-kerberos
Author: Stefan Richter
Author-email: stefan@02strich.de
License: MIT
Keywords: django,kerberos,authentication,auth
Platform: UNKNOWN
Classifier: Development Status :: 5 - Production/Stable
Classifier: Environment :: Web Environment
Classifier: Programming Language :: Python
Classifier: Programming Language :: Python :: 2
Classifier: Framework :: Django
Classifier: Intended Audience :: Developers
Classifier: Intended Audience :: System Administrators
Classifier: License :: OSI Approved :: MIT License
Classifier: Topic :: Internet :: WWW/HTTP
Classifier: Topic :: Software Development :: Libraries :: Python Modules
